{
  "emojis": {
    "upvote": {
      "id": "713823817004220416",
      "karma": 1
    },
    "downvote": {
      "id": "713824298275569734",
      "karma": -1
    }
  },
  "leaderboard": {
    "emojis": {
      "positive": "<:upvote:713823817004220416>",
      "negative": "<:downvote:713824298275569734>"
    },
    "top": {
      "podium": 3,
      "total": 21
    }
  },
  "graphs": {
    "limits": {
      "days": 7
    }
  },
  "lang": {
    "footer": "Pending karma is karma that is temporarily being stored by the bot until it can be sent to the database. Your upvotes on your own messages and bot votes do not count towards karma.",
    "web_panel": {
      "leaderboard": "https://g8c-bot.web.app/karma/leaderboard",
      "user_lookup": "https://g8c-bot.web.app/karma/user"
    }
  },
  "colours": {
    "karma": "#d223d2"
  }
}